{
	"arcgis_catalog": "http://trc.i2.unlv.edu/arcgis/rest/services",
	"approval_gpservice": "http://trc.i2.unlv.edu/arcgis/rest/services/NDOTUDLv1Srvs/ApproveJob/GPServer/UpdateStatus",
	"features": [
		{
			"name": "Roadways",
			"service": "CSAMockAlfo/Roadway",
			"category": "Misc",
			"lyrFile": "CSAMockAlfo_Roadway.lyr",
			"color": "#ABCDEF",
			"enabledOnLoad": false,
			"layers": [
				
				{
					"id": 0,
					"type": "line",
					"color": "#000000",
					"width": 2,
					"opacity": 1.0,
					"definitionExpression": "1=1",
					"fields": [
						{"name": "OBJECTID", "desc": "Object ID"}
						
					]
				}
			]
		},
		{
			"name": "Nevada Districts",
			"color": "#009999",
			"service": "CSAMockAlfo/nevadadistricts",
			"category": "Misc",
			"lyrFile": "CSAMockAlfo_Districts.lyr",
			"enabledOnLoad": false,
			"layers": [
				{
					"id": 0,
					"type": "polygon",
					"color": [0, 100, 100, 0.1],
					"outline": "#009999",
					"definitionExpression": "1=1",
					"fields": [
						{"name": "FID", "desc": "FID"},
						{"name": "DISTRICT_N", "desc": "District Number"}
					]
				},
				{
					"id": 1,
					"type": "polygon",
					"color": [0, 150, 150, 0.1],
					"outline": "#00FFFF",
					"definitionExpression": "1=1",
					"fields": [
						{"name": "OBJECTID", "desc": "Object ID"},
						{"name": "PARENT_CD", "desc": "PARENT_CD"},
						{"name": "PARENT_NAM", "desc": "PARENT_NAM"},
						{"name": "SHAPE_Area", "desc": "Shape Area"}
					]
				}
			]
		},
		{
			"name": "Water",
			"service": "NDOTUDLv1Srvs/SUE_DevApproval",
			"category": "SUE Data",
			"lyrFile": "",
			"color": "#0000FF",
			"enabledOnLoad": true,
			"layers": [
				{
					"id": 0,
					"type": "point",
					"color": "#0000FF",
					"size": 2,
					"definitionExpression": "1=1",
					"fields": [
						{"name": "NDOTUDLv1.DBO.WaterPoints.OBJECTID", "desc": "Object ID"},
						{"name": "NDOTUDLv1.DBO.WaterPoints.JobID", "desc": "Job ID"},
						{"name": "NDOTUDLv1.DBO.WaterPoints.Diameter_Size", "desc": "Diameter Size"},
						{"name": "NDOTUDLv1.DBO.WaterPoints.Status", "desc": "Status"},
						{"name": "NDOTUDLv1.DBO.WaterPoints.Material", "desc": "Material"},
						{"name": "NDOTUDLv1.DBO.WaterPoints.Rel_Horizontal_Pos", "desc": "Rel Horizontal Pos"},
						{"name": "NDOTUDLv1.DBO.WaterPoints.Rel_Vertical_Pos", "desc": "Rel Vertical Pos"},
						{"name": "NDOTUDLv1.DBO.WaterPoints.Depth_Of_Cover", "desc": "Depth Of Cover"},
						{"name": "NDOTUDLv1.DBO.WaterPoints.Tunnel_Casing", "desc": "Tunnel Casing"},
						{"name": "NDOTUDLv1.DBO.WaterPoints.Tunnel_Dimension", "desc": "Tunnel Dimension"},
						{"name": "NDOTUDLv1.DBO.WaterPoints.Northing", "desc": "Northing"},
						{"name": "NDOTUDLv1.DBO.WaterPoints.Easting", "desc": "Easting"},
						{"name": "NDOTUDLv1.DBO.WaterPoints.Notes", "desc": "Notes"}
					]
				},
				{
					"id": 7,
					"type": "line",
					"color": "#0000FF",
					"width": 2,
					"opacity": 1.0,
					"definitionExpression": "1=1",
					"fields": [
						{"name": "NDOTUDLv1.DBO.WaterLines.OBJECTID", "desc": "Object ID"},
						{"name": "NDOTUDLv1.DBO.WaterLines.JobID", "desc": "Job ID"},
						{"name": "NDOTUDLv1.DBO.WaterLines.Diameter_Size", "desc": "Diameter Size"},
						{"name": "NDOTUDLv1.DBO.WaterLines.Status", "desc": "Status"},
						{"name": "NDOTUDLv1.DBO.WaterLines.Material", "desc": "Material"},
						{"name": "NDOTUDLv1.DBO.WaterLines.Rel_Horizontal_Pos", "desc": "Rel Horizontal Pos"},
						{"name": "NDOTUDLv1.DBO.WaterLines.Rel_Vertical_Pos", "desc": "Rel Vertical Pos"},
						{"name": "NDOTUDLv1.DBO.WaterLines.Depth_Of_Cover", "desc": "Depth Of Cover"},
						{"name": "NDOTUDLv1.DBO.WaterLines.Tunnel_Casing", "desc": "Tunnel Casing"},
						{"name": "NDOTUDLv1.DBO.WaterLines.Tunnel_Dimension", "desc": "Tunnel Dimension"},
						{"name": "NDOTUDLv1.DBO.WaterLines.Northing", "desc": "Northing"},
						{"name": "NDOTUDLv1.DBO.WaterLines.Easting", "desc": "Easting"},
						{"name": "NDOTUDLv1.DBO.WaterLines.Notes", "desc": "Notes"}
					]
				}
			]
		},

		{
			"name": "Waste Water",
			"color": "#009900",
			"service": "NDOTUDLv1Srvs/SUE_DevApproval",
			"category": "SUE Data",
			"lyrFile": "",
			"enabledOnLoad": true,
			"layers": [
				{
					"id": 1,
					"type": "point",
					"color": "#009900",
					"size": 2,
					"definitionExpression": "1=1",
					"fields": [
						{"name": "NDOTUDLv1.DBO.WasteWaterPoints.OBJECTID", "desc": "Object ID"},
						{"name": "NDOTUDLv1.DBO.WasteWaterPoints.JobID", "desc": "Job ID"},
						{"name": "NDOTUDLv1.DBO.WasteWaterPoints.Diameter_Size", "desc": "Diameter Size"},
						{"name": "NDOTUDLv1.DBO.WasteWaterPoints.Status", "desc": "Status"},
						{"name": "NDOTUDLv1.DBO.WasteWaterPoints.Material", "desc": "Material"},
						{"name": "NDOTUDLv1.DBO.WasteWaterPoints.Rel_Horizontal_Pos", "desc": "Rel Horizontal Pos"},
						{"name": "NDOTUDLv1.DBO.WasteWaterPoints.Rel_Vertical_Pos", "desc": "Rel Vertical Pos"},
						{"name": "NDOTUDLv1.DBO.WasteWaterPoints.Depth_Of_Cover", "desc": "Depth Of Cover"},
						{"name": "NDOTUDLv1.DBO.WasteWaterPoints.Tunnel_Casing", "desc": "Tunnel Casing"},
						{"name": "NDOTUDLv1.DBO.WasteWaterPoints.Tunnel_Dimension", "desc": "Tunnel Dimension"},
						{"name": "NDOTUDLv1.DBO.WasteWaterPoints.Northing", "desc": "Northing"},
						{"name": "NDOTUDLv1.DBO.WasteWaterPoints.Easting", "desc": "Easting"},
						{"name": "NDOTUDLv1.DBO.WasteWaterPoints.Notes", "desc": "Notes"}
					]
				},
				{
					"id": 8,
					"type": "line",
					"color": "#009900",
					"width": 2,
					"opacity": 1.0,
					"definitionExpression": "1=1",
					"fields": [
						{"name": "NDOTUDLv1.DBO.WasteWaterLines.OBJECTID", "desc": "Object ID"},
						{"name": "NDOTUDLv1.DBO.WasteWaterLines.JobID", "desc": "Job ID"},
						{"name": "NDOTUDLv1.DBO.WasteWaterLines.Diameter_Size", "desc": "Diameter Size"},
						{"name": "NDOTUDLv1.DBO.WasteWaterLines.Status", "desc": "Status"},
						{"name": "NDOTUDLv1.DBO.WasteWaterLines.Material", "desc": "Material"},
						{"name": "NDOTUDLv1.DBO.WasteWaterLines.Rel_Horizontal_Pos", "desc": "Rel Horizontal Pos"},
						{"name": "NDOTUDLv1.DBO.WasteWaterLines.Rel_Vertical_Pos", "desc": "Rel Vertical Pos"},
						{"name": "NDOTUDLv1.DBO.WasteWaterLines.Depth_Of_Cover", "desc": "Depth Of Cover"},
						{"name": "NDOTUDLv1.DBO.WasteWaterLines.Tunnel_Casing", "desc": "Tunnel Casing"},
						{"name": "NDOTUDLv1.DBO.WasteWaterLines.Tunnel_Dimension", "desc": "Tunnel Dimension"},
						{"name": "NDOTUDLv1.DBO.WasteWaterLines.Notes", "desc": "Notes"}
					]
				}
			]
		},
		{
			"name": "Telecom",
			"color": "#E68A3E",
			"service": "NDOTUDLv1Srvs/SUE_DevApproval",
			"category": "SUE Data",
			"lyrFile": "",
			"enabledOnLoad": true,
			"layers": [
				{
					"id": 2,
					"type": "point",
					"color": "#E68A3E",
					"size": 2,
					"definitionExpression": "1=1",
					"fields": [
						{"name": "NDOTUDLv1.DBO.TelecomPoints.OBJECTID", "desc": "Object ID"},
						{"name": "NDOTUDLv1.DBO.TelecomPoints.JobID", "desc": "Job ID"},
						{"name": "NDOTUDLv1.DBO.TelecomPoints.Diameter_Size", "desc": "Diameter Size"},
						{"name": "NDOTUDLv1.DBO.TelecomPoints.Status", "desc": "Status"},
						{"name": "NDOTUDLv1.DBO.TelecomPoints.Material", "desc": "Material"},
						{"name": "NDOTUDLv1.DBO.TelecomPoints.Rel_Horizontal_Pos", "desc": "Rel Horizontal Pos"},
						{"name": "NDOTUDLv1.DBO.TelecomPoints.Rel_Vertical_Pos", "desc": "Rel Vertical Pos"},
						{"name": "NDOTUDLv1.DBO.TelecomPoints.Depth_Of_Cover", "desc": "Depth Of Cover"},
						{"name": "NDOTUDLv1.DBO.TelecomPoints.Northing", "desc": "Northing"},
						{"name": "NDOTUDLv1.DBO.TelecomPoints.Easting", "desc": "Easting"},
						{"name": "NDOTUDLv1.DBO.TelecomPoints.Notes", "desc": "Notes"}
					]
				},
				{
					"id": 9,
					"type": "line",
					"color": "#E68A3E",
					"width": 2,
					"opacity": 1.0,
					"definitionExpression": "1=1",
					"fields": [
						{"name": "NDOTUDLv1.DBO.TelecomLines.OBJECTID", "desc": "Object ID"},
						{"name": "NDOTUDLv1.DBO.TelecomLines.JobID", "desc": "Job ID"},
						{"name": "NDOTUDLv1.DBO.TelecomLines.Diameter_Size", "desc": "Diameter Size"},
						{"name": "NDOTUDLv1.DBO.TelecomLines.Status", "desc": "Status"},
						{"name": "NDOTUDLv1.DBO.TelecomLines.Material", "desc": "Material"},
						{"name": "NDOTUDLv1.DBO.TelecomLines.Rel_Horizontal_Pos", "desc": "Rel Horizontal Pos"},
						{"name": "NDOTUDLv1.DBO.TelecomLines.Rel_Vertical_Pos", "desc": "Rel Vertical Pos"},
						{"name": "NDOTUDLv1.DBO.TelecomLines.Depth_Of_Cover", "desc": "Depth Of Cover"},
						{"name": "NDOTUDLv1.DBO.TelecomLines.Notes", "desc": "Notes"}
					]
				}
			]
		},
		{
			"name": "Petrol",
			"color": "#E6E600",
			"service": "NDOTUDLv1Srvs/SUE_DevApproval",
			"category": "SUE Data",
			"lyrFile": "",
			"enabledOnLoad": true,
			"layers": [
				{
					"id": 3,
					"type": "point",
					"color": "#E6E600",
					"size": 2,
					"definitionExpression": "1=1",
					"fields": [
						{"name": "NDOTUDLv1.DBO.PetrolPoints.OBJECTID", "desc": "Object ID"},
						{"name": "NDOTUDLv1.DBO.PetrolPoints.JobID", "desc": "Job ID"},
						{"name": "NDOTUDLv1.DBO.PetrolPoints.Diameter_Size", "desc": "Diameter Size"},
						{"name": "NDOTUDLv1.DBO.PetrolPoints.Status", "desc": "Status"},
						{"name": "NDOTUDLv1.DBO.PetrolPoints.Material", "desc": "Material"},
						{"name": "NDOTUDLv1.DBO.PetrolPoints.Rel_Horizontal_Pos", "desc": "Rel Horizontal Pos"},
						{"name": "NDOTUDLv1.DBO.PetrolPoints.Rel_Vertical_Pos", "desc": "Rel Vertical Pos"},
						{"name": "NDOTUDLv1.DBO.PetrolPoints.Depth_Of_Cover", "desc": "Depth Of Cover"},
						{"name": "NDOTUDLv1.DBO.PetrolPoints.Northing", "desc": "Northing"},
						{"name": "NDOTUDLv1.DBO.PetrolPoints.Easting", "desc": "Easting"},
						{"name": "NDOTUDLv1.DBO.PetrolPoints.Notes", "desc": "Notes"}
					]
				},
				{
					"id": 10,
					"type": "line",
					"color": "#E6E600",
					"width": 2,
					"opacity": 1.0,
					"definitionExpression": "1=1",
					"fields": [
						{"name": "NDOTUDLv1.DBO.PetrolLines.OBJECTID", "desc": "Object ID"},
						{"name": "NDOTUDLv1.DBO.PetrolLines.JobID", "desc": "Job ID"},
						{"name": "NDOTUDLv1.DBO.PetrolLines.Diameter_Size", "desc": "Diameter Size"},
						{"name": "NDOTUDLv1.DBO.PetrolLines.Status", "desc": "Status"},
						{"name": "NDOTUDLv1.DBO.PetrolLines.Material", "desc": "Material"},
						{"name": "NDOTUDLv1.DBO.PetrolLines.Rel_Horizontal_Pos", "desc": "Rel Horizontal Pos"},
						{"name": "NDOTUDLv1.DBO.PetrolLines.Rel_Vertical_Pos", "desc": "Rel Vertical Pos"},
						{"name": "NDOTUDLv1.DBO.PetrolLines.Depth_Of_Cover", "desc": "Depth Of Cover"},
						{"name": "NDOTUDLv1.DBO.PetrolLines.Notes", "desc": "Notes"}
					]
				}
			]
		},
		{
			"name": "Gas",
			"color": "#FFFF66",
			"service": "NDOTUDLv1Srvs/SUE_DevApproval",
			"category": "SUE Data",
			"lyrFile": "",
			"enabledOnLoad": true,
			"layers": [
				{
					"id": 4,
					"type": "point",
					"color": "#FFFF66",
					"size": 2,
					"definitionExpression": "1=1",
					"fields": [
						{"name": "NDOTUDLv1.DBO.GasPoints.OBJECTID", "desc": "Object ID"},
						{"name": "NDOTUDLv1.DBO.GasPoints.JobID", "desc": "Job ID"},
						{"name": "NDOTUDLv1.DBO.GasPoints.Diameter_Size", "desc": "Diameter Size"},
						{"name": "NDOTUDLv1.DBO.GasPoints.Status", "desc": "Status"},
						{"name": "NDOTUDLv1.DBO.GasPoints.Material", "desc": "Material"},
						{"name": "NDOTUDLv1.DBO.GasPoints.Rel_Horizontal_Pos", "desc": "Rel Horizontal Pos"},
						{"name": "NDOTUDLv1.DBO.GasPoints.Rel_Vertical_Pos", "desc": "Rel Vertical Pos"},
						{"name": "NDOTUDLv1.DBO.GasPoints.Depth_Of_Cover", "desc": "Depth Of Cover"},
						{"name": "NDOTUDLv1.DBO.GasPoints.Northing", "desc": "Northing"},
						{"name": "NDOTUDLv1.DBO.GasPoints.Easting", "desc": "Easting"},
						{"name": "NDOTUDLv1.DBO.GasPoints.Notes", "desc": "Notes"}
					]
				},
				{
					"id": 11,
					"type": "line",
					"color": "#FFFF66",
					"width": 2,
					"opacity": 1.0,
					"definitionExpression": "1=1",
					"fields": [
						{"name": "NDOTUDLv1.DBO.GasLines.OBJECTID", "desc": "Object ID"},
						{"name": "NDOTUDLv1.DBO.GasLines.JobID", "desc": "Job ID"},
						{"name": "NDOTUDLv1.DBO.GasLines.Diameter_Size", "desc": "Diameter Size"},
						{"name": "NDOTUDLv1.DBO.GasLines.Status", "desc": "Status"},
						{"name": "NDOTUDLv1.DBO.GasLines.Material", "desc": "Material"},
						{"name": "NDOTUDLv1.DBO.GasLines.Rel_Horizontal_Pos", "desc": "Rel Horizontal Pos"},
						{"name": "NDOTUDLv1.DBO.GasLines.Rel_Vertical_Pos", "desc": "Rel Vertical Pos"},
						{"name": "NDOTUDLv1.DBO.GasLines.Depth_Of_Cover", "desc": "Depth Of Cover"},
						{"name": "NDOTUDLv1.DBO.GasLines.Notes", "desc": "Notes"}
					]
				}
			]
		},
		{
			"name": "Electric",
			"color": "#BA0000",
			"service": "NDOTUDLv1Srvs/SUE_DevApproval",
			"category": "SUE Data",
			"lyrFile": "",
			"enabledOnLoad": true,
			"layers": [
				{
					"id": 5,
					"type": "point",
					"color": "#BA0000",
					"size": 2,
					"definitionExpression": "1=1",
					"fields": [
						{"name": "NDOTUDLv1.DBO.ElectricPoints.OBJECTID", "desc": "Object ID"},
						{"name": "NDOTUDLv1.DBO.ElectricPoints.JobID", "desc": "Job ID"},
						{"name": "NDOTUDLv1.DBO.ElectricPoints.Diameter_Size", "desc": "Diameter Size"},
						{"name": "NDOTUDLv1.DBO.ElectricPoints.Status", "desc": "Status"},
						{"name": "NDOTUDLv1.DBO.ElectricPoints.Material", "desc": "Material"},
						{"name": "NDOTUDLv1.DBO.ElectricPoints.Rel_Horizontal_Pos", "desc": "Rel Horizontal Pos"},
						{"name": "NDOTUDLv1.DBO.ElectricPoints.Rel_Vertical_Pos", "desc": "Rel Vertical Pos"},
						{"name": "NDOTUDLv1.DBO.ElectricPoints.Depth_Of_Cover", "desc": "Depth Of Cover"},
						{"name": "NDOTUDLv1.DBO.ElectricPoints.Northing", "desc": "Northing"},
						{"name": "NDOTUDLv1.DBO.ElectricPoints.Easting", "desc": "Easting"},
						{"name": "NDOTUDLv1.DBO.ElectricPoints.Notes", "desc": "Notes"}
					]
				},
				{
					"id": 12,
					"type": "line",
					"color": "#BA0000",
					"width": 2,
					"opacity": 1.0,
					"definitionExpression": "1=1",
					"fields": [
						{"name": "NDOTUDLv1.DBO.ElectricLines.OBJECTID", "desc": "Object ID"},
						{"name": "NDOTUDLv1.DBO.ElectricLines.JobID", "desc": "Job ID"},
						{"name": "NDOTUDLv1.DBO.ElectricLines.Diameter_Size", "desc": "Diameter Size"},
						{"name": "NDOTUDLv1.DBO.ElectricLines.Status", "desc": "Status"},
						{"name": "NDOTUDLv1.DBO.ElectricLines.Material", "desc": "Material"},
						{"name": "NDOTUDLv1.DBO.ElectricLines.Rel_Horizontal_Pos", "desc": "Rel Horizontal Pos"},
						{"name": "NDOTUDLv1.DBO.ElectricLines.Rel_Vertical_Pos", "desc": "Rel Vertical Pos"},
						{"name": "NDOTUDLv1.DBO.ElectricLines.Depth_Of_Cover", "desc": "Depth Of Cover"},
						{"name": "NDOTUDLv1.DBO.ElectricLines.Notes", "desc": "Notes"}
					]
				}
			]
		},
		{
			"name": "CmnUnk",
			"color": "#BA00BA",
			"service": "NDOTUDLv1Srvs/SUE_DevApproval",
			"category": "SUE Data",
			"lyrFile": "",
			"enabledOnLoad": true,
			"layers": [
				{
					"id": 6,
					"type": "point",
					"color": "#BA00BA",
					"size": 2,
					"definitionExpression": "1=1",
					"fields": [
						{"name": "NDOTUDLv1.DBO.CmnUnkPoints.OBJECTID", "desc": "Object ID"},
						{"name": "NDOTUDLv1.DBO.CmnUnkPoints.JobID", "desc": "Job ID"},
						{"name": "NDOTUDLv1.DBO.CmnUnkPoints.Notes", "desc": "Notes"}
					]
				},
				{
					"id": 13,
					"type": "line",
					"color": "#BA00BA",
					"width": 2,
					"opacity": 1.0,
					"definitionExpression": "1=1",
					"fields": [
						{"name": "NDOTUDLv1.DBO.CmnUnkLines.OBJECTID", "desc": "Object ID"},
						{"name": "NDOTUDLv1.DBO.CmnUnkLines.JobID", "desc": "Job ID"},
						{"name": "NDOTUDLv1.DBO.CmnUnkLines.Notes", "desc": "Notes"}
					]
				}
			]
		},
		




		{
			"name": "Water",
			"service": "NDOTUDLv1Srvs/Survey_DevApproval",
			"category": "Survey Data",
			"lyrFile": "",
			"color": "#0000FF",
			"enabledOnLoad": true,
			"layers": [
				{
					"id": 0,
					"type": "point",
					"color": "#0000FF",
					"size": 2,
					"definitionExpression": "1=1",
					"fields": [
						{"name": "NDOTUDLv1.DBO.WaterPoints.OBJECTID", "desc": "Object ID"},
						{"name": "NDOTUDLv1.DBO.WaterPoints.JobID", "desc": "Job ID"},
						{"name": "NDOTUDLv1.DBO.WaterPoints.Diameter_Size", "desc": "Diameter Size"},
						{"name": "NDOTUDLv1.DBO.WaterPoints.Status", "desc": "Status"},
						{"name": "NDOTUDLv1.DBO.WaterPoints.Material", "desc": "Material"},
						{"name": "NDOTUDLv1.DBO.WaterPoints.Rel_Horizontal_Pos", "desc": "Rel Horizontal Pos"},
						{"name": "NDOTUDLv1.DBO.WaterPoints.Rel_Vertical_Pos", "desc": "Rel Vertical Pos"},
						{"name": "NDOTUDLv1.DBO.WaterPoints.Depth_Of_Cover", "desc": "Depth Of Cover"},
						{"name": "NDOTUDLv1.DBO.WaterPoints.Tunnel_Casing", "desc": "Tunnel Casing"},
						{"name": "NDOTUDLv1.DBO.WaterPoints.Tunnel_Dimension", "desc": "Tunnel Dimension"},
						{"name": "NDOTUDLv1.DBO.WaterPoints.Northing", "desc": "Northing"},
						{"name": "NDOTUDLv1.DBO.WaterPoints.Easting", "desc": "Easting"},
						{"name": "NDOTUDLv1.DBO.WaterPoints.Notes", "desc": "Notes"}
					]
				},
				{
					"id": 6,
					"type": "line",
					"color": "#0000FF",
					"width": 2,
					"opacity": 1.0,
					"definitionExpression": "1=1",
					"fields": [
						{"name": "NDOTUDLv1.DBO.WaterLines.OBJECTID", "desc": "Object ID"},
						{"name": "NDOTUDLv1.DBO.WaterLines.JobID", "desc": "Job ID"},
						{"name": "NDOTUDLv1.DBO.WaterLines.Diameter_Size", "desc": "Diameter Size"},
						{"name": "NDOTUDLv1.DBO.WaterLines.Status", "desc": "Status"},
						{"name": "NDOTUDLv1.DBO.WaterLines.Material", "desc": "Material"},
						{"name": "NDOTUDLv1.DBO.WaterLines.Rel_Horizontal_Pos", "desc": "Rel Horizontal Pos"},
						{"name": "NDOTUDLv1.DBO.WaterLines.Rel_Vertical_Pos", "desc": "Rel Vertical Pos"},
						{"name": "NDOTUDLv1.DBO.WaterLines.Depth_Of_Cover", "desc": "Depth Of Cover"},
						{"name": "NDOTUDLv1.DBO.WaterLines.Tunnel_Casing", "desc": "Tunnel Casing"},
						{"name": "NDOTUDLv1.DBO.WaterLines.Tunnel_Dimension", "desc": "Tunnel Dimension"},
						{"name": "NDOTUDLv1.DBO.WaterLines.Notes", "desc": "Notes"}
					]
				}
			]
		},

		{
			"name": "Waste Water",
			"color": "#009900",
			"service": "NDOTUDLv1Srvs/Survey_DevApproval",
			"category": "Survey Data",
			"lyrFile": "",
			"enabledOnLoad": true,
			"layers": [
				{
					"id": 1,
					"type": "point",
					"color": "#009900",
					"size": 2,
					"definitionExpression": "1=1",
					"fields": [
						{"name": "NDOTUDLv1.DBO.WasteWaterPoints.OBJECTID", "desc": "Object ID"},
						{"name": "NDOTUDLv1.DBO.WasteWaterPoints.JobID", "desc": "Job ID"},
						{"name": "NDOTUDLv1.DBO.WasteWaterPoints.Diameter_Size", "desc": "Diameter Size"},
						{"name": "NDOTUDLv1.DBO.WasteWaterPoints.Status", "desc": "Status"},
						{"name": "NDOTUDLv1.DBO.WasteWaterPoints.Material", "desc": "Material"},
						{"name": "NDOTUDLv1.DBO.WasteWaterPoints.Rel_Horizontal_Pos", "desc": "Rel Horizontal Pos"},
						{"name": "NDOTUDLv1.DBO.WasteWaterPoints.Rel_Vertical_Pos", "desc": "Rel Vertical Pos"},
						{"name": "NDOTUDLv1.DBO.WasteWaterPoints.Depth_Of_Cover", "desc": "Depth Of Cover"},
						{"name": "NDOTUDLv1.DBO.WasteWaterPoints.Tunnel_Casing", "desc": "Tunnel Casing"},
						{"name": "NDOTUDLv1.DBO.WasteWaterPoints.Tunnel_Dimension", "desc": "Tunnel Dimension"},
						{"name": "NDOTUDLv1.DBO.WasteWaterPoints.Northing", "desc": "Northing"},
						{"name": "NDOTUDLv1.DBO.WasteWaterPoints.Easting", "desc": "Easting"},
						{"name": "NDOTUDLv1.DBO.WasteWaterPoints.Notes", "desc": "Notes"}
					]
				},
				{
					"id": 7,
					"type": "line",
					"color": "#009900",
					"width": 2,
					"opacity": 1.0,
					"definitionExpression": "1=1",
					"fields": [
						{"name": "NDOTUDLv1.DBO.WasteWaterLines.OBJECTID", "desc": "Object ID"},
						{"name": "NDOTUDLv1.DBO.WasteWaterLines.JobID", "desc": "Job ID"},
						{"name": "NDOTUDLv1.DBO.WasteWaterLines.Diameter_Size", "desc": "Diameter Size"},
						{"name": "NDOTUDLv1.DBO.WasteWaterLines.Status", "desc": "Status"},
						{"name": "NDOTUDLv1.DBO.WasteWaterLines.Material", "desc": "Material"},
						{"name": "NDOTUDLv1.DBO.WasteWaterLines.Rel_Horizontal_Pos", "desc": "Rel Horizontal Pos"},
						{"name": "NDOTUDLv1.DBO.WasteWaterLines.Rel_Vertical_Pos", "desc": "Rel Vertical Pos"},
						{"name": "NDOTUDLv1.DBO.WasteWaterLines.Depth_Of_Cover", "desc": "Depth Of Cover"},
						{"name": "NDOTUDLv1.DBO.WasteWaterLines.Tunnel_Casing", "desc": "Tunnel Casing"},
						{"name": "NDOTUDLv1.DBO.WasteWaterLines.Tunnel_Dimension", "desc": "Tunnel Dimension"},
						{"name": "NDOTUDLv1.DBO.WasteWaterLines.Notes", "desc": "Notes"}
					]
				}
			]
		},
		{
			"name": "Telecom",
			"color": "#E68A3E",
			"service": "NDOTUDLv1Srvs/Survey_DevApproval",
			"category": "Survey Data",
			"lyrFile": "",
			"enabledOnLoad": true,
			"layers": [
				{
					"id": 2,
					"type": "point",
					"color": "#E68A3E",
					"size": 2,
					"definitionExpression": "1=1",
					"fields": [
						{"name": "NDOTUDLv1.DBO.TelecomPoints.OBJECTID", "desc": "Object ID"},
						{"name": "NDOTUDLv1.DBO.TelecomPoints.JobID", "desc": "Job ID"},
						{"name": "NDOTUDLv1.DBO.TelecomPoints.Diameter_Size", "desc": "Diameter Size"},
						{"name": "NDOTUDLv1.DBO.TelecomPoints.Status", "desc": "Status"},
						{"name": "NDOTUDLv1.DBO.TelecomPoints.Material", "desc": "Material"},
						{"name": "NDOTUDLv1.DBO.TelecomPoints.Rel_Horizontal_Pos", "desc": "Rel Horizontal Pos"},
						{"name": "NDOTUDLv1.DBO.TelecomPoints.Rel_Vertical_Pos", "desc": "Rel Vertical Pos"},
						{"name": "NDOTUDLv1.DBO.TelecomPoints.Depth_Of_Cover", "desc": "Depth Of Cover"},
						{"name": "NDOTUDLv1.DBO.TelecomPoints.Northing", "desc": "Northing"},
						{"name": "NDOTUDLv1.DBO.TelecomPoints.Easting", "desc": "Easting"},
						{"name": "NDOTUDLv1.DBO.TelecomPoints.Notes", "desc": "Notes"}
					]
				},
				{
					"id": 8,
					"type": "line",
					"color": "#E68A3E",
					"width": 2,
					"opacity": 1.0,
					"definitionExpression": "1=1",
					"fields": [
						{"name": "NDOTUDLv1.DBO.TelecomLines.OBJECTID", "desc": "Object ID"},
						{"name": "NDOTUDLv1.DBO.TelecomLines.JobID", "desc": "Job ID"},
						{"name": "NDOTUDLv1.DBO.TelecomLines.Diameter_Size", "desc": "Diameter Size"},
						{"name": "NDOTUDLv1.DBO.TelecomLines.Status", "desc": "Status"},
						{"name": "NDOTUDLv1.DBO.TelecomLines.Material", "desc": "Material"},
						{"name": "NDOTUDLv1.DBO.TelecomLines.Rel_Horizontal_Pos", "desc": "Rel Horizontal Pos"},
						{"name": "NDOTUDLv1.DBO.TelecomLines.Rel_Vertical_Pos", "desc": "Rel Vertical Pos"},
						{"name": "NDOTUDLv1.DBO.TelecomLines.Depth_Of_Cover", "desc": "Depth Of Cover"},
						{"name": "NDOTUDLv1.DBO.TelecomLines.Notes", "desc": "Notes"}
					]
				}
			]
		},
		{
			"name": "Petrol",
			"color": "#E6E600",
			"service": "NDOTUDLv1Srvs/Survey_DevApproval",
			"category": "Survey Data",
			"lyrFile": "",
			"enabledOnLoad": true,
			"layers": [
				{
					"id": 3,
					"type": "point",
					"color": "#E6E600",
					"size": 2,
					"definitionExpression": "1=1",
					"fields": [
						{"name": "NDOTUDLv1.DBO.PetrolPoints.OBJECTID", "desc": "Object ID"},
						{"name": "NDOTUDLv1.DBO.PetrolPoints.JobID", "desc": "Job ID"},
						{"name": "NDOTUDLv1.DBO.PetrolPoints.Diameter_Size", "desc": "Diameter Size"},
						{"name": "NDOTUDLv1.DBO.PetrolPoints.Status", "desc": "Status"},
						{"name": "NDOTUDLv1.DBO.PetrolPoints.Material", "desc": "Material"},
						{"name": "NDOTUDLv1.DBO.PetrolPoints.Rel_Horizontal_Pos", "desc": "Rel Horizontal Pos"},
						{"name": "NDOTUDLv1.DBO.PetrolPoints.Rel_Vertical_Pos", "desc": "Rel Vertical Pos"},
						{"name": "NDOTUDLv1.DBO.PetrolPoints.Depth_Of_Cover", "desc": "Depth Of Cover"},
						{"name": "NDOTUDLv1.DBO.PetrolPoints.Northing", "desc": "Northing"},
						{"name": "NDOTUDLv1.DBO.PetrolPoints.Easting", "desc": "Easting"},
						{"name": "NDOTUDLv1.DBO.PetrolPoints.Notes", "desc": "Notes"}
					]
				},
				{
					"id": 9,
					"type": "line",
					"color": "#E6E600",
					"width": 2,
					"opacity": 1.0,
					"definitionExpression": "1=1",
					"fields": [
						{"name": "NDOTUDLv1.DBO.PetrolLines.OBJECTID", "desc": "Object ID"},
						{"name": "NDOTUDLv1.DBO.PetrolLines.JobID", "desc": "Job ID"},
						{"name": "NDOTUDLv1.DBO.PetrolLines.Diameter_Size", "desc": "Diameter Size"},
						{"name": "NDOTUDLv1.DBO.PetrolLines.Status", "desc": "Status"},
						{"name": "NDOTUDLv1.DBO.PetrolLines.Material", "desc": "Material"},
						{"name": "NDOTUDLv1.DBO.PetrolLines.Rel_Horizontal_Pos", "desc": "Rel Horizontal Pos"},
						{"name": "NDOTUDLv1.DBO.PetrolLines.Rel_Vertical_Pos", "desc": "Rel Vertical Pos"},
						{"name": "NDOTUDLv1.DBO.PetrolLines.Depth_Of_Cover", "desc": "Depth Of Cover"},
						{"name": "NDOTUDLv1.DBO.PetrolLines.Notes", "desc": "Notes"}
					]
				}
			]
		},
		{
			"name": "Gas",
			"color": "#FFFF66",
			"service": "NDOTUDLv1Srvs/Survey_DevApproval",
			"category": "Survey Data",
			"lyrFile": "",
			"enabledOnLoad": true,
			"layers": [
				{
					"id": 4,
					"type": "point",
					"color": "#FFFF66",
					"size": 2,
					"definitionExpression": "1=1",
					"fields": [
						{"name": "NDOTUDLv1.DBO.GasPoints.OBJECTID", "desc": "Object ID"},
						{"name": "NDOTUDLv1.DBO.GasPoints.JobID", "desc": "Job ID"},
						{"name": "NDOTUDLv1.DBO.GasPoints.Diameter_Size", "desc": "Diameter Size"},
						{"name": "NDOTUDLv1.DBO.GasPoints.Status", "desc": "Status"},
						{"name": "NDOTUDLv1.DBO.GasPoints.Material", "desc": "Material"},
						{"name": "NDOTUDLv1.DBO.GasPoints.Rel_Horizontal_Pos", "desc": "Rel Horizontal Pos"},
						{"name": "NDOTUDLv1.DBO.GasPoints.Rel_Vertical_Pos", "desc": "Rel Vertical Pos"},
						{"name": "NDOTUDLv1.DBO.GasPoints.Depth_Of_Cover", "desc": "Depth Of Cover"},
						{"name": "NDOTUDLv1.DBO.GasPoints.Northing", "desc": "Northing"},
						{"name": "NDOTUDLv1.DBO.GasPoints.Easting", "desc": "Easting"},
						{"name": "NDOTUDLv1.DBO.GasPoints.Notes", "desc": "Notes"}
					]
				},
				{
					"id": 10,
					"type": "line",
					"color": "#FFFF66",
					"width": 2,
					"opacity": 1.0,
					"definitionExpression": "1=1",
					"fields": [
						{"name": "NDOTUDLv1.DBO.GasLines.OBJECTID", "desc": "Object ID"},
						{"name": "NDOTUDLv1.DBO.GasLines.JobID", "desc": "Job ID"},
						{"name": "NDOTUDLv1.DBO.GasLines.Diameter_Size", "desc": "Diameter Size"},
						{"name": "NDOTUDLv1.DBO.GasLines.Status", "desc": "Status"},
						{"name": "NDOTUDLv1.DBO.GasLines.Material", "desc": "Material"},
						{"name": "NDOTUDLv1.DBO.GasLines.Rel_Horizontal_Pos", "desc": "Rel Horizontal Pos"},
						{"name": "NDOTUDLv1.DBO.GasLines.Rel_Vertical_Pos", "desc": "Rel Vertical Pos"},
						{"name": "NDOTUDLv1.DBO.GasLines.Depth_Of_Cover", "desc": "Depth Of Cover"},
						{"name": "NDOTUDLv1.DBO.GasLines.Notes", "desc": "Notes"}
					]
				}
			]
		},
		{
			"name": "Electric",
			"color": "#BA0000",
			"service": "NDOTUDLv1Srvs/Survey_DevApproval",
			"category": "Survey Data",
			"lyrFile": "",
			"enabledOnLoad": true,
			"layers": [
				{
					"id": 5,
					"type": "point",
					"color": "#BA0000",
					"size": 2,
					"definitionExpression": "1=1",
					"fields": [
						{"name": "NDOTUDLv1.DBO.ElectricPoints.OBJECTID", "desc": "Object ID"},
						{"name": "NDOTUDLv1.DBO.ElectricPoints.JobID", "desc": "Job ID"},
						{"name": "NDOTUDLv1.DBO.ElectricPoints.Diameter_Size", "desc": "Diameter Size"},
						{"name": "NDOTUDLv1.DBO.ElectricPoints.Status", "desc": "Status"},
						{"name": "NDOTUDLv1.DBO.ElectricPoints.Material", "desc": "Material"},
						{"name": "NDOTUDLv1.DBO.ElectricPoints.Rel_Horizontal_Pos", "desc": "Rel Horizontal Pos"},
						{"name": "NDOTUDLv1.DBO.ElectricPoints.Rel_Vertical_Pos", "desc": "Rel Vertical Pos"},
						{"name": "NDOTUDLv1.DBO.ElectricPoints.Depth_Of_Cover", "desc": "Depth Of Cover"},
						{"name": "NDOTUDLv1.DBO.ElectricPoints.Northing", "desc": "Northing"},
						{"name": "NDOTUDLv1.DBO.ElectricPoints.Easting", "desc": "Easting"},
						{"name": "NDOTUDLv1.DBO.ElectricPoints.Notes", "desc": "Notes"}
					]
				},
				{
					"id": 11,
					"type": "line",
					"color": "#BA0000",
					"width": 2,
					"opacity": 1.0,
					"definitionExpression": "1=1",
					"fields": [
						{"name": "NDOTUDLv1.DBO.ElectricLines.OBJECTID", "desc": "Object ID"},
						{"name": "NDOTUDLv1.DBO.ElectricLines.JobID", "desc": "Job ID"},
						{"name": "NDOTUDLv1.DBO.ElectricLines.Diameter_Size", "desc": "Diameter Size"},
						{"name": "NDOTUDLv1.DBO.ElectricLines.Status", "desc": "Status"},
						{"name": "NDOTUDLv1.DBO.ElectricLines.Material", "desc": "Material"},
						{"name": "NDOTUDLv1.DBO.ElectricLines.Rel_Horizontal_Pos", "desc": "Rel Horizontal Pos"},
						{"name": "NDOTUDLv1.DBO.ElectricLines.Rel_Vertical_Pos", "desc": "Rel Vertical Pos"},
						{"name": "NDOTUDLv1.DBO.ElectricLines.Depth_Of_Cover", "desc": "Depth Of Cover"},
						{"name": "NDOTUDLv1.DBO.ElectricLines.Notes", "desc": "Notes"}
					]
				}
			]
		},




		{
			"name": "SUE Bounds",
			"color": "#990000",
			"service": "NDOTUDLv1Srvs/SUE_DevApproval",
			"category": "Project Bounds",
			"lyrFile": "",
			"enabledOnLoad": true,
			"isProject": true,
			"layers": [
				{
					"id": 14,
					"type": "polygon",
					"color": [255, 0, 0, 0.1],
					"outline": [255, 0, 0, 1],
					"definitionExpression": "1=1",
					"fields": [
						{"name": "NDOTUDLv1.DBO.Projects.OBJECTID", "desc": "Object ID"},
						{"name": "NDOTUDLv1.DBO.Projects.JobID", "desc": "Job ID"},
						{"name": "NDOTUDLv1.DBO.Projects.UploadedBy", "desc": "Uploaded By"},
						{"name": "NDOTUDLv1.DBO.Projects.UploadDate", "desc": "Upload Date"},
						{"name": "NDOTUDLv1.DBO.Projects.AwaitingApproval", "desc": "Awaiting Approval"},
						{"name": "NDOTUDLv1.DBO.Projects.Approved", "desc": "Approved"},
						{"name": "NDOTUDLv1.DBO.Projects.ApprovedBy", "desc": "Approved By"},
						{"name": "NDOTUDLv1.DBO.Projects.ApprovalDate", "desc": "Approval Date"},
						{"name": "NDOTUDLv1.DBO.Projects.PermitNumber", "desc": "Permit Number"},
						{"name": "NDOTUDLv1.DBO.Projects.OwnerInfo", "desc": "Owner Info"},
						{"name": "NDOTUDLv1.DBO.Projects.EasementInfo", "desc": "Easement Info"},
						{"name": "NDOTUDLv1.DBO.Projects.Notes", "desc": "Notes"}
					]
				}
			],
			"linkTo": {
				"title": "See Project",
				"category": "SUE Data",
				"field": "JobID"
			}
		},
		{
			"name": "Survey Bounds",
			"color": "#990000",
			"service": "NDOTUDLv1Srvs/Survey_DevApproval",
			"category": "Project Bounds",
			"lyrFile": "",
			"enabledOnLoad": true,
			"isProject": true,
			"layers": [
				{
					"id": 12,
					"type": "polygon",
					"color": [255, 0, 0, 0.1],
					"outline": [255, 0, 0, 1],
					"definitionExpression": "1=1",
					"fields": [
						{"name": "NDOTUDLv1.DBO.Projects.OBJECTID", "desc": "Object ID"},
						{"name": "NDOTUDLv1.DBO.Projects.JobID", "desc": "Job ID"},
						{"name": "NDOTUDLv1.DBO.Projects.UploadedBy", "desc": "Uploaded By"},
						{"name": "NDOTUDLv1.DBO.Projects.UploadDate", "desc": "Upload Date"},
						{"name": "NDOTUDLv1.DBO.Projects.AwaitingApproval", "desc": "Awaiting Approval"},
						{"name": "NDOTUDLv1.DBO.Projects.Approved", "desc": "Approved"},
						{"name": "NDOTUDLv1.DBO.Projects.ApprovedBy", "desc": "Approved By"},
						{"name": "NDOTUDLv1.DBO.Projects.ApprovalDate", "desc": "Approval Date"},
						{"name": "NDOTUDLv1.DBO.Projects.PermitNumber", "desc": "Permit Number"},
						{"name": "NDOTUDLv1.DBO.Projects.OwnerInfo", "desc": "Owner Info"},
						{"name": "NDOTUDLv1.DBO.Projects.EasementInfo", "desc": "Easement Info"},
						{"name": "NDOTUDLv1.DBO.Projects.Notes", "desc": "Notes"}
					]
				}
			],
			"linkTo": {
				"title": "See Project",
				"category": "Survey Data",
				"field": "JobID"
			}
		}

		
	]
}